{"temperatuur": "99", "datum": "2014/01/01"},{"temperatuur": "103", "datum": "2014/01/02"},{"temperatuur": "122", "datum": "2014/01/03"},{"temperatuur": "93", "datum": "2014/01/04"},{"temperatuur": "84", "datum": "2014/01/05"},{"temperatuur": "145", "datum": "2014/01/06"},{"temperatuur": "123", "datum": "2014/01/07"},{"temperatuur": "100", "datum": "2014/01/08"},{"temperatuur": "121", "datum": "2014/01/09"},{"temperatuur": "88", "datum": "2014/01/10"},{"temperatuur": "78", "datum": "2014/01/11"},{"temperatuur": "62", "datum": "2014/01/12"},{"temperatuur": "99", "datum": "2014/01/13"},{"temperatuur": "71", "datum": "2014/01/14"},{"temperatuur": "64", "datum": "2014/01/15"},{"temperatuur": "89", "datum": "2014/01/16"},{"temperatuur": "90", "datum": "2014/01/17"},{"temperatuur": "86", "datum": "2014/01/18"},{"temperatuur": "71", "datum": "2014/01/19"},{"temperatuur": "60", "datum": "2014/01/20"},{"temperatuur": "54", "datum": "2014/01/21"},{"temperatuur": "43", "datum": "2014/01/22"},{"temperatuur": "52", "datum": "2014/01/23"},{"temperatuur": "67", "datum": "2014/01/24"},{"temperatuur": "63", "datum": "2014/01/25"},{"temperatuur": "68", "datum": "2014/01/26"},{"temperatuur": "62", "datum": "2014/01/27"},{"temperatuur": "68", "datum": "2014/01/28"},{"temperatuur": "25", "datum": "2014/01/29"},{"temperatuur": "50", "datum": "2014/01/30"},{"temperatuur": "74", "datum": "2014/01/31"},{"temperatuur": "84", "datum": "2014/02/01"},{"temperatuur": "80", "datum": "2014/02/02"},{"temperatuur": "82", "datum": "2014/02/03"},{"temperatuur": "94", "datum": "2014/02/04"},{"temperatuur": "104", "datum": "2014/02/05"},{"temperatuur": "96", "datum": "2014/02/06"},{"temperatuur": "103", "datum": "2014/02/07"},{"temperatuur": "90", "datum": "2014/02/08"},{"temperatuur": "76", "datum": "2014/02/09"},{"temperatuur": "90", "datum": "2014/02/10"},{"temperatuur": "83", "datum": "2014/02/11"},{"temperatuur": "91", "datum": "2014/02/12"},{"temperatuur": "69", "datum": "2014/02/13"},{"temperatuur": "88", "datum": "2014/02/14"},{"temperatuur": "134", "datum": "2014/02/15"},{"temperatuur": "94", "datum": "2014/02/16"},{"temperatuur": "104", "datum": "2014/02/17"},{"temperatuur": "80", "datum": "2014/02/18"},{"temperatuur": "110", "datum": "2014/02/19"},{"temperatuur": "100", "datum": "2014/02/20"},{"temperatuur": "103", "datum": "2014/02/21"},{"temperatuur": "103", "datum": "2014/02/22"},{"temperatuur": "118", "datum": "2014/02/23"},{"temperatuur": "126", "datum": "2014/02/24"},{"temperatuur": "126", "datum": "2014/02/25"},{"temperatuur": "111", "datum": "2014/02/26"},{"temperatuur": "78", "datum": "2014/02/27"},{"temperatuur": "85", "datum": "2014/02/28"},{"temperatuur": "82", "datum": "2014/03/01"},{"temperatuur": "98", "datum": "2014/03/02"},{"temperatuur": "99", "datum": "2014/03/03"},{"temperatuur": "107", "datum": "2014/03/04"},{"temperatuur": "126", "datum": "2014/03/05"},{"temperatuur": "137", "datum": "2014/03/06"},{"temperatuur": "128", "datum": "2014/03/07"},{"temperatuur": "160", "datum": "2014/03/08"},{"temperatuur": "195", "datum": "2014/03/09"},{"temperatuur": "180", "datum": "2014/03/10"},{"temperatuur": "144", "datum": "2014/03/11"},{"temperatuur": "168", "datum": "2014/03/12"},{"temperatuur": "168", "datum": "2014/03/13"},{"temperatuur": "120", "datum": "2014/03/14"},{"temperatuur": "118", "datum": "2014/03/15"},{"temperatuur": "122", "datum": "2014/03/16"},{"temperatuur": "120", "datum": "2014/03/17"},{"temperatuur": "105", "datum": "2014/03/18"},{"temperatuur": "159", "datum": "2014/03/19"},{"temperatuur": "212", "datum": "2014/03/20"},{"temperatuur": "110", "datum": "2014/03/21"},{"temperatuur": "105", "datum": "2014/03/22"},{"temperatuur": "95", "datum": "2014/03/23"},{"temperatuur": "109", "datum": "2014/03/24"},{"temperatuur": "108", "datum": "2014/03/25"},{"temperatuur": "96", "datum": "2014/03/26"},{"temperatuur": "137", "datum": "2014/03/27"},{"temperatuur": "173", "datum": "2014/03/28"},{"temperatuur": "192", "datum": "2014/03/29"},{"temperatuur": "202", "datum": "2014/03/30"},{"temperatuur": "204", "datum": "2014/03/31"},{"temperatuur": "204", "datum": "2014/04/01"},{"temperatuur": "215", "datum": "2014/04/02"},{"temperatuur": "227", "datum": "2014/04/03"},{"temperatuur": "152", "datum": "2014/04/04"},{"temperatuur": "177", "datum": "2014/04/05"},{"temperatuur": "177", "datum": "2014/04/06"},{"temperatuur": "212", "datum": "2014/04/07"},{"temperatuur": "138", "datum": "2014/04/08"},{"temperatuur": "148", "datum": "2014/04/09"},{"temperatuur": "154", "datum": "2014/04/10"},{"temperatuur": "153", "datum": "2014/04/11"},{"temperatuur": "158", "datum": "2014/04/12"},{"temperatuur": "131", "datum": "2014/04/13"},{"temperatuur": "117", "datum": "2014/04/14"},{"temperatuur": "107", "datum": "2014/04/15"},{"temperatuur": "143", "datum": "2014/04/16"},{"temperatuur": "176", "datum": "2014/04/17"},{"temperatuur": "121", "datum": "2014/04/18"},{"temperatuur": "166", "datum": "2014/04/19"},{"temperatuur": "207", "datum": "2014/04/20"},{"temperatuur": "158", "datum": "2014/04/21"},{"temperatuur": "190", "datum": "2014/04/22"},{"temperatuur": "211", "datum": "2014/04/23"},{"temperatuur": "205", "datum": "2014/04/24"},{"temperatuur": "237", "datum": "2014/04/25"},{"temperatuur": "176", "datum": "2014/04/26"},{"temperatuur": "153", "datum": "2014/04/27"},{"temperatuur": "169", "datum": "2014/04/28"},{"temperatuur": "175", "datum": "2014/04/29"},{"temperatuur": "179", "datum": "2014/04/30"},{"temperatuur": "183", "datum": "2014/05/01"},{"temperatuur": "122", "datum": "2014/05/02"},{"temperatuur": "137", "datum": "2014/05/03"},{"temperatuur": "137", "datum": "2014/05/04"},{"temperatuur": "184", "datum": "2014/05/05"},{"temperatuur": "178", "datum": "2014/05/06"},{"temperatuur": "162", "datum": "2014/05/07"},{"temperatuur": "134", "datum": "2014/05/08"},{"temperatuur": "161", "datum": "2014/05/09"},{"temperatuur": "156", "datum": "2014/05/10"},{"temperatuur": "117", "datum": "2014/05/11"},{"temperatuur": "146", "datum": "2014/05/12"},{"temperatuur": "150", "datum": "2014/05/13"},{"temperatuur": "139", "datum": "2014/05/14"},{"temperatuur": "150", "datum": "2014/05/15"},{"temperatuur": "183", "datum": "2014/05/16"},{"temperatuur": "207", "datum": "2014/05/17"},{"temperatuur": "231", "datum": "2014/05/18"},{"temperatuur": "243", "datum": "2014/05/19"},{"temperatuur": "271", "datum": "2014/05/20"},{"temperatuur": "215", "datum": "2014/05/21"},{"temperatuur": "230", "datum": "2014/05/22"},{"temperatuur": "207", "datum": "2014/05/23"},{"temperatuur": "196", "datum": "2014/05/24"},{"temperatuur": "213", "datum": "2014/05/25"},{"temperatuur": "223", "datum": "2014/05/26"},{"temperatuur": "174", "datum": "2014/05/27"},{"temperatuur": "146", "datum": "2014/05/28"},{"temperatuur": "118", "datum": "2014/05/29"},{"temperatuur": "169", "datum": "2014/05/30"},{"temperatuur": "194", "datum": "2014/05/31"},{"temperatuur": "187", "datum": "2014/06/01"},{"temperatuur": "206", "datum": "2014/06/02"},{"temperatuur": "210", "datum": "2014/06/03"},{"temperatuur": "178", "datum": "2014/06/04"},{"temperatuur": "178", "datum": "2014/06/05"},{"temperatuur": "229", "datum": "2014/06/06"},{"temperatuur": "276", "datum": "2014/06/07"},{"temperatuur": "248", "datum": "2014/06/08"},{"temperatuur": "271", "datum": "2014/06/09"},{"temperatuur": "258", "datum": "2014/06/10"},{"temperatuur": "219", "datum": "2014/06/11"},{"temperatuur": "229", "datum": "2014/06/12"},{"temperatuur": "222", "datum": "2014/06/13"},{"temperatuur": "189", "datum": "2014/06/14"},{"temperatuur": "201", "datum": "2014/06/15"},{"temperatuur": "178", "datum": "2014/06/16"},{"temperatuur": "193", "datum": "2014/06/17"},{"temperatuur": "200", "datum": "2014/06/18"},{"temperatuur": "161", "datum": "2014/06/19"},{"temperatuur": "180", "datum": "2014/06/20"},{"temperatuur": "209", "datum": "2014/06/21"},{"temperatuur": "206", "datum": "2014/06/22"},{"temperatuur": "213", "datum": "2014/06/23"},{"temperatuur": "213", "datum": "2014/06/24"},{"temperatuur": "192", "datum": "2014/06/25"},{"temperatuur": "222", "datum": "2014/06/26"},{"temperatuur": "215", "datum": "2014/06/27"},{"temperatuur": "210", "datum": "2014/06/28"},{"temperatuur": "192", "datum": "2014/06/29"},{"temperatuur": "186", "datum": "2014/06/30"},{"temperatuur": "193", "datum": "2014/07/01"},{"temperatuur": "209", "datum": "2014/07/02"},{"temperatuur": "262", "datum": "2014/07/03"},{"temperatuur": "289", "datum": "2014/07/04"},{"temperatuur": "228", "datum": "2014/07/05"},{"temperatuur": "244", "datum": "2014/07/06"},{"temperatuur": "235", "datum": "2014/07/07"},{"temperatuur": "170", "datum": "2014/07/08"},{"temperatuur": "178", "datum": "2014/07/09"},{"temperatuur": "276", "datum": "2014/07/10"},{"temperatuur": "238", "datum": "2014/07/11"},{"temperatuur": "245", "datum": "2014/07/12"},{"temperatuur": "231", "datum": "2014/07/13"},{"temperatuur": "227", "datum": "2014/07/14"},{"temperatuur": "224", "datum": "2014/07/15"},{"temperatuur": "258", "datum": "2014/07/16"},{"temperatuur": "283", "datum": "2014/07/17"},{"temperatuur": "311", "datum": "2014/07/18"},{"temperatuur": "329", "datum": "2014/07/19"},{"temperatuur": "272", "datum": "2014/07/20"},{"temperatuur": "212", "datum": "2014/07/21"},{"temperatuur": "272", "datum": "2014/07/22"},{"temperatuur": "284", "datum": "2014/07/23"},{"temperatuur": "263", "datum": "2014/07/24"},{"temperatuur": "221", "datum": "2014/07/25"},{"temperatuur": "251", "datum": "2014/07/26"},{"temperatuur": "262", "datum": "2014/07/27"},{"temperatuur": "235", "datum": "2014/07/28"},{"temperatuur": "259", "datum": "2014/07/29"},{"temperatuur": "235", "datum": "2014/07/30"},{"temperatuur": "244", "datum": "2014/07/31"},{"temperatuur": "259", "datum": "2014/08/01"},{"temperatuur": "276", "datum": "2014/08/02"},{"temperatuur": "253", "datum": "2014/08/03"},{"temperatuur": "233", "datum": "2014/08/04"},{"temperatuur": "243", "datum": "2014/08/05"},{"temperatuur": "213", "datum": "2014/08/06"},{"temperatuur": "230", "datum": "2014/08/07"},{"temperatuur": "223", "datum": "2014/08/08"},{"temperatuur": "231", "datum": "2014/08/09"},{"temperatuur": "225", "datum": "2014/08/10"},{"temperatuur": "207", "datum": "2014/08/11"},{"temperatuur": "202", "datum": "2014/08/12"},{"temperatuur": "217", "datum": "2014/08/13"},{"temperatuur": "203", "datum": "2014/08/14"},{"temperatuur": "197", "datum": "2014/08/15"},{"temperatuur": "187", "datum": "2014/08/16"},{"temperatuur": "167", "datum": "2014/08/17"},{"temperatuur": "173", "datum": "2014/08/18"},{"temperatuur": "159", "datum": "2014/08/19"},{"temperatuur": "178", "datum": "2014/08/20"},{"temperatuur": "182", "datum": "2014/08/21"},{"temperatuur": "171", "datum": "2014/08/22"},{"temperatuur": "174", "datum": "2014/08/23"},{"temperatuur": "177", "datum": "2014/08/24"},{"temperatuur": "169", "datum": "2014/08/25"},{"temperatuur": "165", "datum": "2014/08/26"},{"temperatuur": "207", "datum": "2014/08/27"},{"temperatuur": "214", "datum": "2014/08/28"},{"temperatuur": "212", "datum": "2014/08/29"},{"temperatuur": "186", "datum": "2014/08/30"},{"temperatuur": "190", "datum": "2014/08/31"},{"temperatuur": "212", "datum": "2014/09/01"},{"temperatuur": "212", "datum": "2014/09/02"},{"temperatuur": "212", "datum": "2014/09/03"},{"temperatuur": "235", "datum": "2014/09/04"},{"temperatuur": "228", "datum": "2014/09/05"},{"temperatuur": "205", "datum": "2014/09/06"},{"temperatuur": "216", "datum": "2014/09/07"},{"temperatuur": "205", "datum": "2014/09/08"},{"temperatuur": "178", "datum": "2014/09/09"},{"temperatuur": "184", "datum": "2014/09/10"},{"temperatuur": "204", "datum": "2014/09/11"},{"temperatuur": "216", "datum": "2014/09/12"},{"temperatuur": "211", "datum": "2014/09/13"},{"temperatuur": "209", "datum": "2014/09/14"},{"temperatuur": "228", "datum": "2014/09/15"},{"temperatuur": "246", "datum": "2014/09/16"},{"temperatuur": "252", "datum": "2014/09/17"},{"temperatuur": "253", "datum": "2014/09/18"},{"temperatuur": "244", "datum": "2014/09/19"},{"temperatuur": "240", "datum": "2014/09/20"},{"temperatuur": "192", "datum": "2014/09/21"},{"temperatuur": "175", "datum": "2014/09/22"},{"temperatuur": "177", "datum": "2014/09/23"},{"temperatuur": "165", "datum": "2014/09/24"},{"temperatuur": "178", "datum": "2014/09/25"},{"temperatuur": "194", "datum": "2014/09/26"},{"temperatuur": "202", "datum": "2014/09/27"},{"temperatuur": "220", "datum": "2014/09/28"},{"temperatuur": "193", "datum": "2014/09/29"},{"temperatuur": "209", "datum": "2014/09/30"},{"temperatuur": "207", "datum": "2014/10/01"},{"temperatuur": "192", "datum": "2014/10/02"},{"temperatuur": "222", "datum": "2014/10/03"},{"temperatuur": "211", "datum": "2014/10/04"},{"temperatuur": "152", "datum": "2014/10/05"},{"temperatuur": "161", "datum": "2014/10/06"},{"temperatuur": "156", "datum": "2014/10/07"},{"temperatuur": "166", "datum": "2014/10/08"},{"temperatuur": "180", "datum": "2014/10/09"},{"temperatuur": "178", "datum": "2014/10/10"},{"temperatuur": "157", "datum": "2014/10/11"},{"temperatuur": "162", "datum": "2014/10/12"},{"temperatuur": "185", "datum": "2014/10/13"},{"temperatuur": "136", "datum": "2014/10/14"},{"temperatuur": "184", "datum": "2014/10/15"},{"temperatuur": "180", "datum": "2014/10/16"},{"temperatuur": "188", "datum": "2014/10/17"},{"temperatuur": "230", "datum": "2014/10/18"},{"temperatuur": "215", "datum": "2014/10/19"},{"temperatuur": "177", "datum": "2014/10/20"},{"temperatuur": "140", "datum": "2014/10/21"},{"temperatuur": "135", "datum": "2014/10/22"},{"temperatuur": "151", "datum": "2014/10/23"},{"temperatuur": "126", "datum": "2014/10/24"},{"temperatuur": "153", "datum": "2014/10/25"},{"temperatuur": "159", "datum": "2014/10/26"},{"temperatuur": "170", "datum": "2014/10/27"},{"temperatuur": "140", "datum": "2014/10/28"},{"temperatuur": "128", "datum": "2014/10/29"},{"temperatuur": "156", "datum": "2014/10/30"},{"temperatuur": "166", "datum": "2014/10/31"},{"temperatuur": "185", "datum": "2014/11/01"},{"temperatuur": "174", "datum": "2014/11/02"},{"temperatuur": "153", "datum": "2014/11/03"},{"temperatuur": "109", "datum": "2014/11/04"},{"temperatuur": "95", "datum": "2014/11/05"},{"temperatuur": "82", "datum": "2014/11/06"},{"temperatuur": "98", "datum": "2014/11/07"},{"temperatuur": "129", "datum": "2014/11/08"},{"temperatuur": "128", "datum": "2014/11/09"},{"temperatuur": "126", "datum": "2014/11/10"},{"temperatuur": "129", "datum": "2014/11/11"},{"temperatuur": "122", "datum": "2014/11/12"},{"temperatuur": "133", "datum": "2014/11/13"},{"temperatuur": "124", "datum": "2014/11/14"},{"temperatuur": "110", "datum": "2014/11/15"},{"temperatuur": "92", "datum": "2014/11/16"},{"temperatuur": "123", "datum": "2014/11/17"},{"temperatuur": "83", "datum": "2014/11/18"},{"temperatuur": "91", "datum": "2014/11/19"},{"temperatuur": "80", "datum": "2014/11/20"},{"temperatuur": "90", "datum": "2014/11/21"},{"temperatuur": "118", "datum": "2014/11/22"},{"temperatuur": "135", "datum": "2014/11/23"},{"temperatuur": "113", "datum": "2014/11/24"},{"temperatuur": "91", "datum": "2014/11/25"},{"temperatuur": "64", "datum": "2014/11/26"},{"temperatuur": "88", "datum": "2014/11/27"},{"temperatuur": "95", "datum": "2014/11/28"},{"temperatuur": "49", "datum": "2014/11/29"},{"temperatuur": "31", "datum": "2014/11/30"},{"temperatuur": "24", "datum": "2014/12/01"},{"temperatuur": "14", "datum": "2014/12/02"},{"temperatuur": "10", "datum": "2014/12/03"},{"temperatuur": "15", "datum": "2014/12/04"},{"temperatuur": "53", "datum": "2014/12/05"},{"temperatuur": "91", "datum": "2014/12/06"},{"temperatuur": "67", "datum": "2014/12/07"},{"temperatuur": "49", "datum": "2014/12/08"},{"temperatuur": "49", "datum": "2014/12/09"},{"temperatuur": "99", "datum": "2014/12/10"},{"temperatuur": "77", "datum": "2014/12/11"},{"temperatuur": "94", "datum": "2014/12/12"},{"temperatuur": "68", "datum": "2014/12/13"},{"temperatuur": "48", "datum": "2014/12/14"},{"temperatuur": "79", "datum": "2014/12/15"},{"temperatuur": "78", "datum": "2014/12/16"},{"temperatuur": "106", "datum": "2014/12/17"},{"temperatuur": "125", "datum": "2014/12/18"},{"temperatuur": "124", "datum": "2014/12/19"},{"temperatuur": "91", "datum": "2014/12/20"},{"temperatuur": "103", "datum": "2014/12/21"},{"temperatuur": "128", "datum": "2014/12/22"},{"temperatuur": "128", "datum": "2014/12/23"},{"temperatuur": "100", "datum": "2014/12/24"},{"temperatuur": "79", "datum": "2014/12/25"},{"temperatuur": "52", "datum": "2014/12/26"},{"temperatuur": "29", "datum": "2014/12/27"},{"temperatuur": "34", "datum": "2014/12/28"},{"temperatuur": "56", "datum": "2014/12/29"},{"temperatuur": "65", "datum": "2014/12/30"},{"temperatuur": "76", "datum": "2014/12/31"}